{
  "_class": "shapePath",
  "booleanOperation": -1,
  "clippingMaskMode": 0,
  "do_objectID": "B5CE89C3-7E32-4231-914F-9CE653A96D1E",
  "edited": true,
  "exportOptions": {
    "_class": "exportOptions",
    "do_objectID": "CBE865F8-6AEE-472A-B782-7DB3F713055D",
    "exportFormats": [
    ],
    "includedLayerIds": [
    ],
    "layerOptions": 0,
    "shouldTrim": false
  },
  "frame": {
    "_class": "rect",
    "constrainProportions": false,
    "do_objectID": "D8FE8F59-6B29-48A2-8EC7-F6BBC7C4360B",
    "height": 2,
    "width": 360,
    "x": 0,
    "y": 512
  },
  "hasClippingMask": false,
  "isClosed": false,
  "isFixedToViewport": false,
  "isFlippedHorizontal": false,
  "isFlippedVertical": false,
  "isLocked": false,
  "isVisible": true,
  "layerListExpandedType": 0,
  "name": "Line 3",
  "nameIsFixed": false,
  "pointRadiusBehaviour": 1,
  "points": [
    {
      "_class": "curvePoint",
      "cornerRadius": 0,
      "curveFrom": "{2.5263862182822722e-15, 0.5}",
      "curveMode": 1,
      "curveTo": "{2.5263862182822722e-15, 0.5}",
      "hasCurveFrom": false,
      "hasCurveTo": false,
      "point": "{2.5263862182822722e-15, 0.5}"
    },
    {
      "_class": "curvePoint",
      "cornerRadius": 0,
      "curveFrom": "{2.5263862182822722e-15, 0.5}",
      "curveMode": 1,
      "curveTo": "{2.5263862182822722e-15, 0.5}",
      "hasCurveFrom": false,
      "hasCurveTo": false,
      "point": "{1.0000000000000018, 0.5}"
    }
  ],
  "resizingConstraint": 63,
  "resizingType": 0,
  "rotation": 0,
  "shouldBreakMaskChain": false,
  "style": {
    "_class": "style",
    "borderOptions": {
      "_class": "borderOptions",
      "dashPattern": [
      ],
      "do_objectID": "ECBFC9F6-E404-4776-BCF9-1C8921364EC0",
      "isEnabled": false,
      "lineCapStyle": 2,
      "lineJoinStyle": 0
    },
    "borders": [
      {
        "_class": "border",
        "color": {
          "_class": "color",
          "alpha": 1,
          "blue": 0.592,
          "green": 0.592,
          "red": 0.592
        },
        "fillType": 0,
        "isEnabled": true,
        "position": 0,
        "thickness": 1
      }
    ],
    "do_objectID": "364B599B-9DC4-4D60-AC63-8EEC79AC0F01",
    "endMarkerType": 0,
    "fills": [
      {
        "_class": "fill",
        "color": {
          "_class": "color",
          "alpha": 1,
          "blue": 0.847,
          "green": 0.847,
          "red": 0.847
        },
        "fillType": 0,
        "isEnabled": false,
        "noiseIndex": 0,
        "noiseIntensity": 0,
        "patternFillType": 1,
        "patternTileScale": 1
      }
    ],
    "miterLimit": 10,
    "startMarkerType": 0,
    "windingRule": 1
  }
}