{
  "_class": "text",
  "attributedString": {
    "_class": "attributedString",
    "attributes": [
      {
        "_class": "stringAttribute",
        "attributes": {
          "MSAttributedStringColorAttribute": {
            "_class": "color",
            "alpha": 1,
            "blue": 1,
            "green": 1,
            "red": 1
          },
          "MSAttributedStringFontAttribute": {
            "_class": "fontDescriptor",
            "attributes": {
              "name": "HKGrotesk-Bold",
              "size": 14
            }
          },
          "paragraphStyle": {
            "_class": "paragraphStyle",
            "alignment": 0
          },
          "textStyleVerticalAlignmentKey": 0
        },
        "length": 14,
        "location": 0
      }
    ],
    "string": "Hyde Park ($) "
  },
  "automaticallyDrawOnUnderlyingPath": false,
  "booleanOperation": -1,
  "clippingMaskMode": 0,
  "do_objectID": "DB727B9E-74F2-401B-8780-0DD45F6393F4",
  "dontSynchroniseWithSymbol": false,
  "exportOptions": {
    "_class": "exportOptions",
    "exportFormats": [
    ],
    "includedLayerIds": [
    ],
    "layerOptions": 0,
    "shouldTrim": false
  },
  "frame": {
    "_class": "rect",
    "constrainProportions": false,
    "height": 18,
    "width": 88,
    "x": 7,
    "y": 6
  },
  "glyphBounds": "{{1, 2}, {83, 15}}",
  "hasClippingMask": false,
  "isFixedToViewport": false,
  "isFlippedHorizontal": false,
  "isFlippedVertical": false,
  "isLocked": false,
  "isVisible": true,
  "layerListExpandedType": 0,
  "lineSpacingBehaviour": 2,
  "name": "Hyde Park ($)",
  "nameIsFixed": false,
  "resizingConstraint": 47,
  "resizingType": 0,
  "rotation": 0,
  "shouldBreakMaskChain": false,
  "style": {
    "_class": "style",
    "endMarkerType": 0,
    "miterLimit": 10,
    "startMarkerType": 0,
    "textStyle": {
      "_class": "textStyle",
      "encodedAttributes": {
        "MSAttributedStringColorAttribute": {
          "_class": "color",
          "alpha": 1,
          "blue": 1,
          "green": 1,
          "red": 1
        },
        "MSAttributedStringFontAttribute": {
          "_class": "fontDescriptor",
          "attributes": {
            "name": "HKGrotesk-Bold",
            "size": 14
          }
        },
        "paragraphStyle": {
          "_class": "paragraphStyle",
          "alignment": 0
        },
        "textStyleVerticalAlignmentKey": 0
      },
      "verticalAlignment": 0
    },
    "windingRule": 1
  },
  "textBehaviour": 0
}