{
  "_class": "symbolInstance",
  "booleanOperation": -1,
  "clippingMaskMode": 0,
  "do_objectID": "1DDA07CD-F14B-410D-A169-AEA968586541",
  "exportOptions": {
    "_class": "exportOptions",
    "do_objectID": "EC626044-DB33-4C08-BC79-76839ED15303",
    "exportFormats": [
    ],
    "includedLayerIds": [
    ],
    "layerOptions": 0,
    "shouldTrim": false
  },
  "frame": {
    "_class": "rect",
    "constrainProportions": false,
    "do_objectID": "890D4281-EB4C-45D3-93F8-035CF68CCF2E",
    "height": 92,
    "width": 144,
    "x": -44.99999999999997,
    "y": -13
  },
  "hasClippingMask": false,
  "horizontalSpacing": 0,
  "isFixedToViewport": false,
  "isFlippedHorizontal": false,
  "isFlippedVertical": false,
  "isLocked": false,
  "isVisible": true,
  "layerListExpandedType": 0,
  "name": "Image(Gray BG)",
  "nameIsFixed": false,
  "overrideValues": [
  ],
  "resizingConstraint": 63,
  "resizingType": 0,
  "rotation": 0,
  "scale": 1,
  "shouldBreakMaskChain": false,
  "style": {
    "_class": "style",
    "do_objectID": "7A289A44-079B-4F0A-A29B-5351EC1A6298",
    "endMarkerType": 0,
    "miterLimit": 10,
    "startMarkerType": 0,
    "windingRule": 1
  },
  "symbolID": "D8CE79BD-F67F-4A16-88F1-BD8589D152F5",
  "verticalSpacing": 0
}